boe_mcp/__init__.py
boe_mcp/server.py
boe_mcp-0.1.0.dist-info/licenses/LICENSE
boe_mcp-0.1.0.dist-info/METADATA
boe_mcp-0.1.0.dist-info/WHEEL
boe_mcp-0.1.0.dist-info/entry_points.txt
boe_mcp-0.1.0.dist-info/top_level.txt
boe_mcp-0.1.0.dist-info/RECORD
