Metadata-Version: 2.4
Name: boe-mcp
Version: 0.1.0
Summary: BOE API integration with MCP (Model Context Protocol)
License-Expression: MIT
Requires-Python: >=3.10
License-File: LICENSE
Requires-Dist: httpx>=0.28.1
Requires-Dist: mcp[cli]>=1.8.1
Dynamic: license-file
